setup.py
jdoe_yt_downloader/__init__.py
jdoe_yt_downloader/__main__.py
jdoe_yt_downloader.egg-info/PKG-INFO
jdoe_yt_downloader.egg-info/SOURCES.txt
jdoe_yt_downloader.egg-info/dependency_links.txt
jdoe_yt_downloader.egg-info/entry_points.txt
jdoe_yt_downloader.egg-info/not-zip-safe
jdoe_yt_downloader.egg-info/requires.txt
jdoe_yt_downloader.egg-info/top_level.txt