Metadata-Version: 1.0
Name: jdoe-yt-downloader
Version: 0.9.8.3
Summary: Download YT video in mp3 format
Home-page: https://github.com/JohnnyDeeee/YT_MP3_Downloader.git
Author: JohnDoe
Author-email: anotherfakeone@live.nl
License: MIT
Platform: UNKNOWN
